simple_flask_server/__init__.py
simple_flask_server/__main__.py
simple_flask_server-0.0.7.dist-info/METADATA
simple_flask_server-0.0.7.dist-info/WHEEL
simple_flask_server-0.0.7.dist-info/entry_points.txt
simple_flask_server-0.0.7.dist-info/licenses/LICENSE
simple_flask_server-0.0.7.dist-info/RECORD
