Metadata-Version: 2.4
Name: simple-flask-server
Version: 0.0.7
Summary: Using Flask as a lightweight HTTP server in place of Python's built-in http.server
Project-URL: Homepage, https://github.com/atsuoishimoto/simple_flask_server
License-File: LICENSE
Classifier: Development Status :: 3 - Alpha
Classifier: Environment :: Console
Classifier: Environment :: Web Environment
Classifier: License :: OSI Approved :: MIT License
Classifier: Operating System :: OS Independent
Classifier: Programming Language :: Python :: 3
Requires-Python: >=3.10
Requires-Dist: flask>=3.1.1
